{
  "latest": {
    "timestamp": "2026-05-14 01:59:57",
    "cpu_percent": 3.0,
    "ram_percent": 69.6,
    "ram_used_gb": 1.33,
    "ram_total_gb": 1.91,
    "disk_percent": 24.2,
    "disk_free_gb": 36.97,
    "threads": 1,
    "python_procs": [
      {
        "pid": 1341,
        "script": "adaptive_dashboard.py",
        "ram_%": 9.34,
        "cpu_%": 0.4
      },
      {
        "pid": 1377,
        "script": "ai_layer.py",
        "ram_%": 8.05,
        "cpu_%": 0.0
      },
      {
        "pid": 1252,
        "script": "auto_monitor.py",
        "ram_%": 7.88,
        "cpu_%": 0.0
      },
      {
        "pid": 1255,
        "script": "monitor_upgrade.py",
        "ram_%": 7.83,
        "cpu_%": 2.6
      },
      {
        "pid": 1279,
        "script": "telegram_commands.py",
        "ram_%": 7.8,
        "cpu_%": 0.0
      },
      {
        "pid": 1376,
        "script": "master_orchestrator.py",
        "ram_%": 7.48,
        "cpu_%": 0.0
      },
      {
        "pid": 1378,
        "script": "institutional_layer.py",
        "ram_%": 7.31,
        "cpu_%": 0.0
      },
      {
        "pid": 1340,
        "script": "macro_intelligence.py",
        "ram_%": 7.23,
        "cpu_%": 0.0
      },
      {
        "pid": 1276,
        "script": "intraday_engine.py",
        "ram_%": 7.11,
        "cpu_%": 0.0
      },
      {
        "pid": 1290,
        "script": "health_monitor.py",
        "ram_%": 1.71,
        "cpu_%": 0.0
      }
    ]
  },
  "history": [
    {
      "ts": "2026-05-14 01:08:35",
      "cpu": 8.1,
      "ram": 70.0,
      "disk": 24.1
    },
    {
      "ts": "2026-05-14 01:09:07",
      "cpu": 11.5,
      "ram": 70.0,
      "disk": 24.1
    },
    {
      "ts": "2026-05-14 01:09:38",
      "cpu": 4.0,
      "ram": 70.0,
      "disk": 24.1
    },
    {
      "ts": "2026-05-14 01:10:09",
      "cpu": 5.9,
      "ram": 69.9,
      "disk": 24.1
    },
    {
      "ts": "2026-05-14 01:10:40",
      "cpu": 7.0,
      "ram": 69.9,
      "disk": 24.1
    },
    {
      "ts": "2026-05-14 01:11:11",
      "cpu": 1.0,
      "ram": 69.9,
      "disk": 24.1
    },
    {
      "ts": "2026-05-14 01:11:42",
      "cpu": 3.0,
      "ram": 69.9,
      "disk": 24.1
    },
    {
      "ts": "2026-05-14 01:12:13",
      "cpu": 25.0,
      "ram": 69.9,
      "disk": 24.1
    },
    {
      "ts": "2026-05-14 01:12:45",
      "cpu": 1.0,
      "ram": 69.9,
      "disk": 24.1
    },
    {
      "ts": "2026-05-14 01:13:16",
      "cpu": 1.0,
      "ram": 69.9,
      "disk": 24.1
    },
    {
      "ts": "2026-05-14 01:13:47",
      "cpu": 0.0,
      "ram": 69.9,
      "disk": 24.1
    },
    {
      "ts": "2026-05-14 01:14:18",
      "cpu": 0.0,
      "ram": 69.9,
      "disk": 24.1
    },
    {
      "ts": "2026-05-14 01:14:49",
      "cpu": 2.0,
      "ram": 69.9,
      "disk": 24.1
    },
    {
      "ts": "2026-05-14 01:15:20",
      "cpu": 2.0,
      "ram": 69.9,
      "disk": 24.1
    },
    {
      "ts": "2026-05-14 01:15:51",
      "cpu": 1.0,
      "ram": 69.9,
      "disk": 24.1
    },
    {
      "ts": "2026-05-14 01:16:23",
      "cpu": 5.0,
      "ram": 69.9,
      "disk": 24.1
    },
    {
      "ts": "2026-05-14 01:16:54",
      "cpu": 2.0,
      "ram": 69.9,
      "disk": 24.1
    },
    {
      "ts": "2026-05-14 01:17:25",
      "cpu": 50.5,
      "ram": 69.9,
      "disk": 24.1
    },
    {
      "ts": "2026-05-14 01:17:56",
      "cpu": 3.0,
      "ram": 69.9,
      "disk": 24.1
    },
    {
      "ts": "2026-05-14 01:18:27",
      "cpu": 2.0,
      "ram": 69.9,
      "disk": 24.1
    },
    {
      "ts": "2026-05-14 01:18:58",
      "cpu": 1.0,
      "ram": 69.9,
      "disk": 24.1
    },
    {
      "ts": "2026-05-14 01:19:29",
      "cpu": 1.0,
      "ram": 69.9,
      "disk": 24.1
    },
    {
      "ts": "2026-05-14 01:20:00",
      "cpu": 2.0,
      "ram": 69.9,
      "disk": 24.1
    },
    {
      "ts": "2026-05-14 01:20:32",
      "cpu": 1.0,
      "ram": 69.9,
      "disk": 24.1
    },
    {
      "ts": "2026-05-14 01:21:03",
      "cpu": 1.0,
      "ram": 69.9,
      "disk": 24.1
    },
    {
      "ts": "2026-05-14 01:21:34",
      "cpu": 3.0,
      "ram": 69.9,
      "disk": 24.1
    },
    {
      "ts": "2026-05-14 01:22:05",
      "cpu": 1.0,
      "ram": 69.9,
      "disk": 24.1
    },
    {
      "ts": "2026-05-14 01:22:36",
      "cpu": 1.0,
      "ram": 69.9,
      "disk": 24.1
    },
    {
      "ts": "2026-05-14 01:23:07",
      "cpu": 1.0,
      "ram": 69.9,
      "disk": 24.1
    },
    {
      "ts": "2026-05-14 01:23:38",
      "cpu": 5.0,
      "ram": 69.9,
      "disk": 24.1
    },
    {
      "ts": "2026-05-14 01:24:09",
      "cpu": 1.0,
      "ram": 69.9,
      "disk": 24.1
    },
    {
      "ts": "2026-05-14 01:24:40",
      "cpu": 1.0,
      "ram": 69.9,
      "disk": 24.1
    },
    {
      "ts": "2026-05-14 01:25:12",
      "cpu": 4.0,
      "ram": 69.8,
      "disk": 24.1
    },
    {
      "ts": "2026-05-14 01:25:43",
      "cpu": 2.0,
      "ram": 69.8,
      "disk": 24.1
    },
    {
      "ts": "2026-05-14 01:26:14",
      "cpu": 5.0,
      "ram": 69.8,
      "disk": 24.1
    },
    {
      "ts": "2026-05-14 01:26:45",
      "cpu": 22.2,
      "ram": 69.8,
      "disk": 24.1
    },
    {
      "ts": "2026-05-14 01:27:16",
      "cpu": 3.0,
      "ram": 69.8,
      "disk": 24.1
    },
    {
      "ts": "2026-05-14 01:27:47",
      "cpu": 2.0,
      "ram": 69.8,
      "disk": 24.1
    },
    {
      "ts": "2026-05-14 01:28:18",
      "cpu": 20.2,
      "ram": 69.8,
      "disk": 24.1
    },
    {
      "ts": "2026-05-14 01:28:49",
      "cpu": 1.0,
      "ram": 69.8,
      "disk": 24.1
    },
    {
      "ts": "2026-05-14 01:29:20",
      "cpu": 0.0,
      "ram": 69.8,
      "disk": 24.1
    },
    {
      "ts": "2026-05-14 01:29:52",
      "cpu": 11.3,
      "ram": 69.8,
      "disk": 24.1
    },
    {
      "ts": "2026-05-14 01:30:23",
      "cpu": 0.0,
      "ram": 69.8,
      "disk": 24.1
    },
    {
      "ts": "2026-05-14 01:30:54",
      "cpu": 2.0,
      "ram": 69.8,
      "disk": 24.1
    },
    {
      "ts": "2026-05-14 01:31:25",
      "cpu": 4.0,
      "ram": 69.8,
      "disk": 24.1
    },
    {
      "ts": "2026-05-14 01:31:56",
      "cpu": 1.0,
      "ram": 69.8,
      "disk": 24.1
    },
    {
      "ts": "2026-05-14 01:32:27",
      "cpu": 2.0,
      "ram": 69.8,
      "disk": 24.1
    },
    {
      "ts": "2026-05-14 01:32:59",
      "cpu": 18.9,
      "ram": 69.8,
      "disk": 24.1
    },
    {
      "ts": "2026-05-14 01:33:30",
      "cpu": 2.0,
      "ram": 69.8,
      "disk": 24.1
    },
    {
      "ts": "2026-05-14 01:34:01",
      "cpu": 1.0,
      "ram": 69.8,
      "disk": 24.1
    },
    {
      "ts": "2026-05-14 01:34:32",
      "cpu": 23.6,
      "ram": 69.8,
      "disk": 24.1
    },
    {
      "ts": "2026-05-14 01:35:04",
      "cpu": 7.0,
      "ram": 69.8,
      "disk": 24.1
    },
    {
      "ts": "2026-05-14 01:35:35",
      "cpu": 1.0,
      "ram": 69.8,
      "disk": 24.1
    },
    {
      "ts": "2026-05-14 01:36:06",
      "cpu": 5.0,
      "ram": 69.8,
      "disk": 24.1
    },
    {
      "ts": "2026-05-14 01:36:37",
      "cpu": 1.0,
      "ram": 69.8,
      "disk": 24.1
    },
    {
      "ts": "2026-05-14 01:37:08",
      "cpu": 1.0,
      "ram": 69.8,
      "disk": 24.1
    },
    {
      "ts": "2026-05-14 01:37:39",
      "cpu": 4.0,
      "ram": 69.8,
      "disk": 24.1
    },
    {
      "ts": "2026-05-14 01:38:10",
      "cpu": 2.0,
      "ram": 69.8,
      "disk": 24.1
    },
    {
      "ts": "2026-05-14 01:38:41",
      "cpu": 1.0,
      "ram": 69.8,
      "disk": 24.1
    },
    {
      "ts": "2026-05-14 01:39:13",
      "cpu": 4.0,
      "ram": 69.8,
      "disk": 24.1
    },
    {
      "ts": "2026-05-14 01:39:44",
      "cpu": 2.0,
      "ram": 69.8,
      "disk": 24.1
    },
    {
      "ts": "2026-05-14 01:40:15",
      "cpu": 4.0,
      "ram": 69.7,
      "disk": 24.1
    },
    {
      "ts": "2026-05-14 01:40:46",
      "cpu": 2.0,
      "ram": 69.7,
      "disk": 24.1
    },
    {
      "ts": "2026-05-14 01:41:17",
      "cpu": 1.0,
      "ram": 69.7,
      "disk": 24.1
    },
    {
      "ts": "2026-05-14 01:41:48",
      "cpu": 26.0,
      "ram": 69.7,
      "disk": 24.1
    },
    {
      "ts": "2026-05-14 01:42:19",
      "cpu": 2.0,
      "ram": 69.7,
      "disk": 24.1
    },
    {
      "ts": "2026-05-14 01:42:50",
      "cpu": 5.0,
      "ram": 69.7,
      "disk": 24.1
    },
    {
      "ts": "2026-05-14 01:43:21",
      "cpu": 23.8,
      "ram": 69.7,
      "disk": 24.2
    },
    {
      "ts": "2026-05-14 01:43:52",
      "cpu": 2.0,
      "ram": 69.7,
      "disk": 24.2
    },
    {
      "ts": "2026-05-14 01:44:24",
      "cpu": 2.0,
      "ram": 69.7,
      "disk": 24.2
    },
    {
      "ts": "2026-05-14 01:44:55",
      "cpu": 24.0,
      "ram": 69.7,
      "disk": 24.2
    },
    {
      "ts": "2026-05-14 01:45:26",
      "cpu": 7.1,
      "ram": 69.7,
      "disk": 24.2
    },
    {
      "ts": "2026-05-14 01:45:57",
      "cpu": 1.0,
      "ram": 69.7,
      "disk": 24.2
    },
    {
      "ts": "2026-05-14 01:46:28",
      "cpu": 21.0,
      "ram": 69.7,
      "disk": 24.2
    },
    {
      "ts": "2026-05-14 01:46:59",
      "cpu": 2.0,
      "ram": 69.7,
      "disk": 24.2
    },
    {
      "ts": "2026-05-14 01:47:30",
      "cpu": 1.0,
      "ram": 69.7,
      "disk": 24.2
    },
    {
      "ts": "2026-05-14 01:48:01",
      "cpu": 1.0,
      "ram": 69.7,
      "disk": 24.2
    },
    {
      "ts": "2026-05-14 01:48:32",
      "cpu": 2.0,
      "ram": 69.7,
      "disk": 24.2
    },
    {
      "ts": "2026-05-14 01:49:03",
      "cpu": 1.0,
      "ram": 69.7,
      "disk": 24.2
    },
    {
      "ts": "2026-05-14 01:49:35",
      "cpu": 0.0,
      "ram": 69.7,
      "disk": 24.2
    },
    {
      "ts": "2026-05-14 01:50:06",
      "cpu": 1.0,
      "ram": 69.7,
      "disk": 24.2
    },
    {
      "ts": "2026-05-14 01:50:37",
      "cpu": 1.0,
      "ram": 69.7,
      "disk": 24.2
    },
    {
      "ts": "2026-05-14 01:51:08",
      "cpu": 1.0,
      "ram": 69.7,
      "disk": 24.2
    },
    {
      "ts": "2026-05-14 01:51:39",
      "cpu": 2.0,
      "ram": 69.7,
      "disk": 24.2
    },
    {
      "ts": "2026-05-14 01:52:10",
      "cpu": 1.0,
      "ram": 69.7,
      "disk": 24.2
    },
    {
      "ts": "2026-05-14 01:52:41",
      "cpu": 1.0,
      "ram": 69.7,
      "disk": 24.2
    },
    {
      "ts": "2026-05-14 01:53:12",
      "cpu": 5.0,
      "ram": 69.7,
      "disk": 24.2
    },
    {
      "ts": "2026-05-14 01:53:43",
      "cpu": 0.0,
      "ram": 69.6,
      "disk": 24.2
    },
    {
      "ts": "2026-05-14 01:54:14",
      "cpu": 1.0,
      "ram": 69.6,
      "disk": 24.2
    },
    {
      "ts": "2026-05-14 01:54:46",
      "cpu": 1.0,
      "ram": 69.6,
      "disk": 24.2
    },
    {
      "ts": "2026-05-14 01:55:17",
      "cpu": 2.0,
      "ram": 69.6,
      "disk": 24.2
    },
    {
      "ts": "2026-05-14 01:55:48",
      "cpu": 0.0,
      "ram": 69.6,
      "disk": 24.2
    },
    {
      "ts": "2026-05-14 01:56:19",
      "cpu": 1.0,
      "ram": 69.6,
      "disk": 24.2
    },
    {
      "ts": "2026-05-14 01:56:50",
      "cpu": 1.0,
      "ram": 69.6,
      "disk": 24.2
    },
    {
      "ts": "2026-05-14 01:57:21",
      "cpu": 2.0,
      "ram": 69.6,
      "disk": 24.2
    },
    {
      "ts": "2026-05-14 01:57:52",
      "cpu": 1.0,
      "ram": 69.6,
      "disk": 24.2
    },
    {
      "ts": "2026-05-14 01:58:23",
      "cpu": 1.0,
      "ram": 69.6,
      "disk": 24.2
    },
    {
      "ts": "2026-05-14 01:58:54",
      "cpu": 1.0,
      "ram": 69.6,
      "disk": 24.2
    },
    {
      "ts": "2026-05-14 01:59:26",
      "cpu": 2.0,
      "ram": 69.6,
      "disk": 24.2
    },
    {
      "ts": "2026-05-14 01:59:57",
      "cpu": 3.0,
      "ram": 69.6,
      "disk": 24.2
    }
  ]
}